setup.py
astrococo.egg-info/PKG-INFO
astrococo.egg-info/SOURCES.txt
astrococo.egg-info/dependency_links.txt
astrococo.egg-info/entry_points.txt
astrococo.egg-info/requires.txt
astrococo.egg-info/top_level.txt
coco/__init__.py
coco/coco.py
coco/version.py