Metadata-Version: 1.1
Name: astrococo
Version: 0.0.2b1
Summary: astronomical coordinate conversion.
Home-page: https://github.com/mrtommyb/coco
Author: Tom Barclay
Author-email: tom@tombarclay.com
License: MIT
Platform: UNKNOWN
Classifier: Development Status :: 5 - Production/Stable
Classifier: License :: OSI Approved :: MIT License
Classifier: Operating System :: OS Independent
Classifier: Programming Language :: Python
Classifier: Intended Audience :: Science/Research
Classifier: Topic :: Scientific/Engineering :: Astronomy
